langchain_lakefs/__init__.py
langchain_lakefs/chat_models.py
langchain_lakefs/document_loaders.py
langchain_lakefs/embeddings.py
langchain_lakefs/py.typed
langchain_lakefs/retrievers.py
langchain_lakefs/toolkits.py
langchain_lakefs/tools.py
langchain_lakefs/vectorstores.py
langchain_lakefs-0.1.1.dist-info/LICENSE
langchain_lakefs-0.1.1.dist-info/METADATA
langchain_lakefs-0.1.1.dist-info/WHEEL
langchain_lakefs-0.1.1.dist-info/RECORD
