Metadata-Version: 2.3
Name: langchain-lakefs
Version: 0.1.1
Summary: An integration package connecting LakeFS and LangChain
License: MIT
Requires-Python: >=3.9,<4.0
Classifier: License :: OSI Approved :: MIT License
Classifier: Programming Language :: Python :: 3
Classifier: Programming Language :: Python :: 3.9
Classifier: Programming Language :: Python :: 3.10
Classifier: Programming Language :: Python :: 3.11
Classifier: Programming Language :: Python :: 3.12
Classifier: Programming Language :: Python :: 3.13
Requires-Dist: lakefs (>=0.9.0,<0.10.0)
Requires-Dist: langchain-core (>=0.3.15,<0.4.0)
Project-URL: Repository, https://github.com/treeverse/langchain-lakefs
Project-URL: Release Notes, https://github.com/langchain-ai/langchain/releases?q=tag%3A%22lakefs%3D%3D0%22&expanded=true
Project-URL: Source Code, https://github.com/langchain-ai/langchain/tree/master/libs/partners/lakefs
